README.md
setup.py
app/__init__.py
app/api/__init__.py
app/api/badges.py
app/api/bootstrap.py
app/api/geokrety.py
app/api/geokrety_types.py
app/api/moves.py
app/api/moves_comments.py
app/api/moves_types.py
app/api/news.py
app/api/news_comments.py
app/api/news_subscriptions.py
app/api/users.py
app/api/helpers/__init__.py
app/api/helpers/auth.py
app/api/helpers/data_layers.py
app/api/helpers/db.py
app/api/helpers/exceptions.py
app/api/helpers/jwt.py
app/api/helpers/permission_manager.py
app/api/helpers/permissions.py
app/api/helpers/utilities.py
app/api/schema/__init__.py
app/api/schema/badges.py
app/api/schema/geokrety.py
app/api/schema/geokrety_types.py
app/api/schema/moves.py
app/api/schema/moves_comments.py
app/api/schema/moves_types.py
app/api/schema/news.py
app/api/schema/news_comments.py
app/api/schema/news_subscriptions.py
app/api/schema/users.py
app/models/__init__.py
app/models/events/__init__.py
app/models/events/badge.py
app/models/events/geokret.py
app/models/events/move.py
app/models/events/move_comment.py
app/models/events/news.py
app/models/events/news_comment.py
app/models/events/news_subscription.py
app/models/events/user.py
app/views/__init__.py
app/views/minio.py
app/views/pika_.py
app/views/regex.py
app/views/sentry.py
geokrety_api.egg-info/PKG-INFO
geokrety_api.egg-info/SOURCES.txt
geokrety_api.egg-info/dependency_links.txt
geokrety_api.egg-info/requires.txt
geokrety_api.egg-info/top_level.txt
tests/__init__.py
tests/hook_main.py
tests/unittests/__init__.py
tests/unittests/setup_database.py
tests/unittests/api/__init__.py
tests/unittests/api/badges/__init__.py
tests/unittests/api/badges/test_badge_collection.py
tests/unittests/api/badges/test_badge_create.py
tests/unittests/api/badges/test_badge_delete.py
tests/unittests/api/badges/test_badge_details.py
tests/unittests/api/badges/test_badge_edit.py
tests/unittests/api/badges/test_badge_links.py
tests/unittests/api/badges/test_badge_relationships.py
tests/unittests/api/geokrety/__init__.py
tests/unittests/api/geokrety/test_geokrety_collection.py
tests/unittests/api/geokrety/test_geokrety_create.py
tests/unittests/api/geokrety/test_geokrety_delete.py
