Metadata-Version: 2.1
Name: geokrety-api
Version: 0.0.2
Summary: GeoKrety JSONAPI server
Home-page: https://github.com/geokrety/geokrety-api
Author: Mathieu Alorent
Author-email: kumy@geokrety.org
License: UNKNOWN
Platform: UNKNOWN
Classifier: Programming Language :: Python :: 3
Classifier: License :: OSI Approved :: MIT License
Classifier: Operating System :: OS Independent
